miniver/__init__.py
miniver/_static_version.py
miniver/_version.py
miniver/app.py
miniver-0.8.0.dist-info/LICENSE
miniver-0.8.0.dist-info/METADATA
miniver-0.8.0.dist-info/WHEEL
miniver-0.8.0.dist-info/entry_points.txt
miniver-0.8.0.dist-info/top_level.txt
miniver-0.8.0.dist-info/RECORD
