Metadata-Version: 2.1
Name: miniver
Version: 0.8.0
Summary: minimal versioning tool
Home-page: https://github.com/jbweston/miniver
Author: Joseph Weston and Christoph Groth
Author-email: joseph@weston.cloud
License: CC0
Platform: UNKNOWN
Classifier: Development Status :: 4 - Beta
Classifier: License :: CC0 1.0 Universal (CC0 1.0) Public Domain Dedication
Classifier: Topic :: Software Development :: Version Control :: Git
Classifier: Intended Audience :: Developers
Classifier: Programming Language :: Python :: 3 :: Only
Classifier: Programming Language :: Python :: 3.5
Classifier: Programming Language :: Python :: 3.6
Classifier: Programming Language :: Python :: 3.7
Classifier: Programming Language :: Python :: 3.8
Classifier: Operating System :: POSIX :: Linux
Classifier: Operating System :: MacOS :: MacOS X
Classifier: Operating System :: Microsoft :: Windows
